{
  "version": 4,
  "updatedAt": "2026-06-27",
  "city": "LBR",
  "attribution": "Données issues de goguelnikov/SpaceInvaders (communauté Space Invader hunters, licence ODbL) et pnote.eu (statuts à jour + identifiants supplémentaires — avec autorisation de l'auteur). Certaines coordonnées dérivées d'OpenStreetMap — licence ODbL.",
  "_baseCount": 8,
  "invaders": [
    {
      "id": "LBR_01",
      "city": "LBR",
      "lat": 43.8578844961,
      "lng": 5.5567263815,
      "status": "ok",
      "points": 40,
      "hint": "",
      "instagramUrl": "https://www.instagram.com/explore/tags/lbr_01/",
      "source": "goguelnikov",
      "statusFromPnote": true
    },
    {
      "id": "LBR_02",
      "city": "LBR",
      "lat": 43.8682998773,
      "lng": 5.1430390458,
      "status": "damaged",
      "points": 50,
      "hint": "",
      "instagramUrl": "https://www.instagram.com/explore/tags/lbr_02/",
      "source": "goguelnikov",
      "statusFromPnote": true
    },
    {
      "id": "LBR_03",
      "city": "LBR",
      "lat": 43.8886259652,
      "lng": 5.2404259571,
      "status": "ok",
      "points": 30,
      "hint": "",
      "instagramUrl": "https://www.instagram.com/explore/tags/lbr_03/",
      "source": "goguelnikov",
      "statusFromPnote": true
    },
    {
      "id": "LBR_04",
      "city": "LBR",
      "lat": 43.9033710594,
      "lng": 5.1903693629,
      "status": "destroyed",
      "points": 20,
      "hint": "",
      "instagramUrl": "https://www.instagram.com/explore/tags/lbr_04/",
      "source": "goguelnikov",
      "statusFromPnote": true
    },
    {
      "id": "LBR_05",
      "city": "LBR",
      "lat": 43.8823674838,
      "lng": 5.3822545252,
      "status": "damaged",
      "points": 30,
      "hint": "",
      "instagramUrl": "https://www.instagram.com/explore/tags/lbr_05/",
      "source": "goguelnikov",
      "statusFromPnote": true
    },
    {
      "id": "LBR_06",
      "city": "LBR",
      "lat": 43.8645147761,
      "lng": 5.6811470386,
      "status": "ok",
      "points": 50,
      "hint": "",
      "instagramUrl": "https://www.instagram.com/explore/tags/lbr_06/",
      "source": "goguelnikov",
      "statusFromPnote": true
    },
    {
      "id": "LBR_07",
      "city": "LBR",
      "lat": 43.8225659574,
      "lng": 5.3062450404,
      "status": "ok",
      "points": 30,
      "hint": "",
      "instagramUrl": "https://www.instagram.com/explore/tags/lbr_07/",
      "source": "goguelnikov",
      "statusFromPnote": true
    },
    {
      "id": "LBR_08",
      "city": "LBR",
      "lat": 43.7948029034,
      "lng": 5.3441769163,
      "status": "destroyed",
      "points": 40,
      "hint": "",
      "instagramUrl": "https://www.instagram.com/explore/tags/lbr_08/",
      "source": "goguelnikov",
      "statusFromPnote": true
    }
  ]
}