{
  "version": 5,
  "updatedAt": "2026-07-19",
  "city": "RN",
  "attribution": "Données issues de goguelnikov/SpaceInvaders (communauté Space Invader hunters, licence ODbL) et pnote.eu (statuts à jour + identifiants supplémentaires — avec autorisation de l'auteur). Certaines coordonnées dérivées d'OpenStreetMap — licence ODbL.",
  "_baseCount": 4,
  "invaders": [
    {
      "id": "RN_01",
      "city": "RN",
      "lat": 48.1137140872,
      "lng": -1.6795195094,
      "status": "ok",
      "points": 30,
      "hint": "",
      "instagramUrl": "https://www.instagram.com/explore/tags/rn_01/",
      "source": "goguelnikov",
      "statusFromPnote": true,
      "photoUrl": "https://www.invader-spotter.art/grosplan/RN/RN_01-grosplan.png",
      "datePosed": "2008-08-27"
    },
    {
      "id": "RN_02",
      "city": "RN",
      "lat": 48.1136095012,
      "lng": -1.6808401318,
      "status": "damaged",
      "points": 30,
      "hint": "",
      "instagramUrl": "https://www.instagram.com/explore/tags/rn_02/",
      "source": "goguelnikov",
      "statusFromPnote": true,
      "photoUrl": "https://www.invader-spotter.art/grosplan/RN/RN_02-grosplan.png",
      "datePosed": "2008-08-28"
    },
    {
      "id": "RN_03",
      "city": "RN",
      "lat": 48.1072988227,
      "lng": -1.6801913284,
      "status": "ok",
      "points": 20,
      "hint": "",
      "instagramUrl": "https://www.instagram.com/explore/tags/rn_03/",
      "source": "goguelnikov",
      "statusFromPnote": true,
      "photoUrl": "https://www.invader-spotter.art/grosplan/RN/RN_03-grosplan.png",
      "datePosed": "2021-05-14"
    },
    {
      "id": "RN_04",
      "city": "RN",
      "lat": 48.108600184,
      "lng": -1.6772238081,
      "status": "ok",
      "points": 30,
      "hint": "",
      "instagramUrl": "https://www.instagram.com/explore/tags/rn_04/",
      "source": "goguelnikov",
      "statusFromPnote": true,
      "photoUrl": "https://www.invader-spotter.art/grosplan/RN/RN_04-grosplan.png",
      "datePosed": "2021-05-14"
    }
  ]
}